Workbook
Name Aporte: 'Projeção financeira'!$D$19
Name patrimonio: 'Projeção financeira'!$D$22
Name qtd_anos: 'Projeção financeira'!$D$20
Name Rendimento_carteira: 'Projeção financeira'!$D$15
Name Salario: 'Projeção financeira'!$D$14
Name sugestao_investimento: 'Projeção financeira'!$D$16
Name taxa_mensal: 'Projeção financeira'!$D$21

Sheet Projeção financeira
B13: Configurações
B14: Salário | D14: 5000
B15: Rendimento carteira | D15: 0.006
B16: Sugestão de investimento | D16: =D14*30% -> 1500
B18: Investimento Mensal
B19: Quanto investir por mês? | D19: 500
B20: Por quantos anos? | D20: 5
B21: Taxa de rendimento mensal? | D21: 0.01079
B22: Patrimônio acumulado? | D22: =FV(taxa_mensal,qtd_anos*12,Aporte*-1) -> 41888.457
B23: Dividendos mensais? | D23: =patrimonio*Rendimento_carteira -> 251.33074
B25: Cenários | D25: Dividendo
A26: 2 | B26: Quanto em 2 anos? | C26: =FV($D$21,$A26*12,$D$19*-1) -> 13613.814 | D26: =C26*Rendimento_carteira -> 81.682882
A27: 5 | B27: Quanto em 5 anos? | C27: =FV($D$21,$A27*12,$D$19*-1) -> 41888.457 | D27: =C27*Rendimento_carteira -> 251.33074
A28: 10 | B28: Quanto em 10 anos? | C28: =FV($D$21,$A28*12,$D$19*-1) -> 121642.11 | D28: =C28*Rendimento_carteira -> 729.85264
A29: 20 | B29: Quanto em 20 anos? | C29: =FV($D$21,$A29*12,$D$19*-1) -> 562599.2 | D29: =C29*Rendimento_carteira -> 3375.5952
A30: 30 | B30: Quanto em 30 anos? | C30: =FV($D$21,$A30*12,$D$19*-1) -> 2161084.8 | D30: =C30*Rendimento_carteira -> 12966.509
B34: PERFIL | C34: Conservador
B35: Valor a ser investido por mês | C35: =Aporte -> 500
B37: TIPO DE FII | C37: Percentual Sugerido | D37: Valores
B38: PAPEL | C38: =VLOOKUP($C$34&"-"&B38,'Planilha de apoio'!$B:$E,4,) -> 0.3 | D38: =C38*$C$35 -> 150
B39: TIJOLO | C39: =VLOOKUP($C$34&"-"&B39,'Planilha de apoio'!$B:$E,4,) -> 0.5 | D39: =C39*$C$35 -> 250
B40: HÍBRIDOS | C40: =VLOOKUP($C$34&"-"&B40,'Planilha de apoio'!$B:$E,4,) -> 0.1 | D40: =C40*$C$35 -> 50
B41: FOFs | C41: =VLOOKUP($C$34&"-"&B41,'Planilha de apoio'!$B:$E,4,) -> 0.1 | D41: =C41*$C$35 -> 50
B42: DESENVOLVIMENTO | C42: =VLOOKUP($C$34&"-"&B42,'Planilha de apoio'!$B:$E,4,) -> 0 | D42: =C42*$C$35 -> 0
B43: HOTELARIAS | C43: =VLOOKUP($C$34&"-"&B43,'Planilha de apoio'!$B:$E,4,) -> 0 | D43: =C43*$C$35 -> 0
D44: =SUM(D38:D43) -> 500

Sheet Planilha de apoio
B2: CHAVE | C2: PERFIL | D2: TIPO DE FII | E2: %
B3: Conservador-PAPEL | C3: Conservador | D3: PAPEL | E3: 0.3
B4: Conservador-TIJOLO | C4: Conservador | D4: TIJOLO | E4: 0.5
B5: Conservador-HÍBRIDOS | C5: Conservador | D5: HÍBRIDOS | E5: 0.1
B6: Conservador-FOFs | C6: Conservador | D6: FOFs | E6: 0.1
B7: Conservador-DESENVOLVIMENTO | C7: Conservador | D7: DESENVOLVIMENTO | E7: 0
B8: Conservador-HOTELARIAS | C8: Conservador | D8: HOTELARIAS | E8: 0
B9: Moderado-PAPEL | C9: Moderado | D9: PAPEL | E9: 0.32
B10: Moderado-TIJOLO | C10: Moderado | D10: TIJOLO | E10: 0.35
B11: Moderado-HÍBRIDOS | C11: Moderado | D11: HÍBRIDOS | E11: 0.08
B12: Moderado-FOFs | C12: Moderado | D12: FOFs | E12: 0.05
B13: Moderado-DESENVOLVIMENTO | C13: Moderado | D13: DESENVOLVIMENTO | E13: 0.1
B14: Moderado-HOTELARIAS | C14: Moderado | D14: HOTELARIAS | E14: 0.1
... B20: Agressivo-HOTELARIAS | C20: Agressivo | D20: HOTELARIAS | E20: 0.1
